csusb/spring-2025/cse-4010/lab/Lab3/Lab3b/fullSubtractor.v
//Module implementing a half-Subtractor
module halfSubtractor(op1, op2, difference, borrow);

    //Inputs for the half-Subtractor
    input op1, op2;

    //Outputs: difference and borrow.
    output difference, borrow;

    assign difference =  op1 ^ op2;     //difference = op1 XOR op2
    assign borrow =  !op1 & op2;        //borrow = NOT(op1) AND op2

endmodule

//Module implementing a full-Subtractor
module fullSubtractor(A, B, BIn, difference, BOut);

    //Inputs for the full-Subtractor.
    input A, B, BIn;

    //Outputs: difference, B out
    output difference, BOut;

    //Wires need to connect the two full-subtractors
    wire c, d, e, f;

    halfSubtractor u1(A, B, c, d);      // C = difference,  d = borrow value
    halfSubtractor u2(c, BIn, e, f);    // The 2nd half-adder will hace c(difference) and BIn as inputs

    assign difference = e;              //difference = e(Differnce 2nd half-subtractor)
    assign BOut =  f | d;               // BOut = f(Borrow value - 2nd half-Subtractor) OR d
    
endmodule

csusb/spring-2025/cse-4010/lab/Lab3/Lab3b/fullSubtractor_tb.v
`timescale 1 ns / 1 ns
`include "fullSubtractor.v"

//Module implementing a testbench for the full-subtractor module
module fullSubtractor_tb;
 
 //Declares three register to hold our temporary values.
 reg A, B, BIn;

 //Declares wires to hold our outputs from the full-subtractors/
 wire difference, BOut;

//Instantiates full-subtractor unit test
 fullSubtractor uut(A, B, BIn, difference, BOut);

 initial begin

    $dumpfile("fullSubtractor_tb.vcd");
    $dumpvars(0, fullSubtractor_tb);
    
    //Following lines of code implement our truth table for the full-Subtractors
    {A, B, BIn} = 3'd0; #20;        //Assign A, B, and BIn to the 3-bit length decimal value 0. A,B,Bin = 000 (0)
    {A, B, BIn} = 3'd1; #20;        //A, B, BIn = 001(1)
    {A, B, BIn} = 3'd2; #20;
    {A, B, BIn} = 3'd3; #20;
    {A, B, BIn} = 3'd4; #20;
    {A, B, BIn} = 3'd5; #20;
    {A, B, BIn} = 3'd6; #20;
    {A, B, BIn} = 3'd7; #20;        //A, B, BIn = 111 (7)
    $display("Finished additions!");    
end

endmodule

csusb/spring-2025/cse-4010/lab/Lab3/Lab3b/fullSubtractor_tb.vcd
$date
	Thu Feb 27 12:41:38 2025
$end
$version
	Icarus Verilog
$end
$timescale
	1ns
$end
$scope module fullSubtractor_tb $end
$var wire 1 ! difference $end
$var wire 1 " BOut $end
$var reg 1 # A $end
$var reg 1 $ B $end
$var reg 1 % BIn $end
$scope module uut $end
$var wire 1 # A $end
$var wire 1 $ B $end
$var wire 1 % BIn $end
$var wire 1 " BOut $end
$var wire 1 ! difference $end
$var wire 1 & f $end
$var wire 1 ' e $end
$var wire 1 ( d $end
$var wire 1 ) c $end
$scope module u1 $end
$var wire 1 ( borrow $end
$var wire 1 ) difference $end
$var wire 1 # op1 $end
$var wire 1 $ op2 $end
$upscope $end
$scope module u2 $end
$var wire 1 & borrow $end
$var wire 1 ' difference $end
$var wire 1 ) op1 $end
$var wire 1 % op2 $end
$upscope $end
$upscope $end
$upscope $end
$enddefinitions $end
$comment Show the parameter values. $end
$dumpall
$end
#0
$dumpvars
0)
0(
0'
0&
0%
0$
0#
0"
0!
$end
#20
1"
1!
1'
1&
1%
#40
1)
1(
1!
1'
0&
1$
0%
#60
0!
0'
1%
#80
0"
0(
1!
1'
1#
0$
0%
#100
0!
0'
1%
#120
0)
0!
0'
1$
0%
#140
1"
1!
1'
1&
1%
