csusb/spring-2025/cse-4010/lab/Lab4/Lab4b/mux8x1.v
//Module implements a 8x1 multiplexer using 3 4x1 multiplexers.
module mux_8x1(a, b, c, d, e, f, g, h, sel0, sel1, sel2, out);

    input a, b, c, d, e, f, g, h, sel0, sel1, sel2;
    output out;
    
    //These wires will act as our two 4x1 multiplexers.
    wire mux1, mux2;

    //Since we need 8 inputs for our 8x1 mux, we need 2 4x1 muxes
    //We use two inner and one outer ternary operator ( ? : ) for each selector in our mux.
    //High voltage returns the expression before the colon and low voltage returns the expressions after
    //The outer ternary operator uses the input sel1 to selects between which group of variable we are going to choose from
    //The two inner ternary operator use the input sel0 to assign a specific input to our mux
    assign mux1 = sel1 ? (sel0 ? d : c) : (sel0 ? b : a);        
    assign mux2 = sel1 ? (sel0 ? h : g) : (sel0 ? f : e);       

    //This is the third mux used to combine inputs/outputs of mux1 and mux2
    assign out =  sel2 ? (sel0 ? mux2 : mux1) : (sel0 ? mux2 : mux1);   

endmodule

csusb/spring-2025/cse-4010/lab/Lab4/Lab4b/mux8x1_tb.v
`timescale 1ns / 1ns
`include "mux8x1.v"

//Module implements a test bench for our 8x1 mux 
module mux8x1_tb;

//Declares 11 input variables and one output variable (O)
reg A, B, C, D, E, F, G, H, Sel0, Sel1, Sel2;
wire O;

mux_8x1 uut(A, B, C, D, E, F, G, H, Sel0, Sel1, Sel2, O);

initial begin
    $dumpfile("mux8x1_tb");
    $dumpvars(0, mux8x1_tb);
    
    //Assign our input values.
    A = 0; B = 1; C = 0; D = 1;
    E = 0; F = 1; G = 0; H = 1;
    
    //Following lines of code assign 3-bit lenght decimal to our Sel2, Sel1 and Sel0 with a 20ns interval
    {Sel2, Sel1, Sel0} = 3'd0; #20;     //Sel2, Sel1, Sel0 = 000 (0) 
    {Sel2, Sel1, Sel0} = 3'd1; #20;     //Sel2, Sel1, Sel0 = 001 (1)
    {Sel2, Sel1, Sel0} = 3'd2; #20;     //Sel2, Sel1, Sel0 = 010 (2)
    {Sel2, Sel1, Sel0} = 3'd3; #20;     //And a similar pattern follows for the remaining values
    {Sel2, Sel1, Sel0} = 3'd4; #20;
    {Sel2, Sel1, Sel0} = 3'd5; #20;
    {Sel2, Sel1, Sel0} = 3'd6; #20;
    {Sel2, Sel1, Sel0} = 3'd7; #20;

    $display("Complete!");
end
endmodule

csusb/spring-2025/cse-4010/lab/Lab4/Lab4b/mux8x1_tb.vcd
$date
	Sat Mar 15 13:20:03 2025
$end
$version
	Icarus Verilog
$end
$timescale
	1ns
$end
$scope module mux8x1_tb $end
$var wire 1 ! O $end
$var reg 1 " A $end
$var reg 1 # B $end
$var reg 1 $ C $end
$var reg 1 % D $end
$var reg 1 & E $end
$var reg 1 ' F $end
$var reg 1 ( G $end
$var reg 1 ) H $end
$var reg 1 * Sel0 $end
$var reg 1 + Sel1 $end
$var reg 1 , Sel2 $end
$scope module uut $end
$var wire 1 " a $end
$var wire 1 # b $end
$var wire 1 $ c $end
$var wire 1 % d $end
$var wire 1 & e $end
$var wire 1 ' f $end
$var wire 1 ( g $end
$var wire 1 ) h $end
$var wire 1 * sel0 $end
$var wire 1 + sel1 $end
$var wire 1 , sel2 $end
$var wire 1 ! out $end
$var wire 1 - mux2 $end
$var wire 1 . mux1 $end
$upscope $end
$upscope $end
$enddefinitions $end
$comment Show the parameter values. $end
$dumpall
$end
#0
$dumpvars
0.
0-
0,
0+
0*
1)
0(
1'
0&
1%
0$
1#
0"
0!
$end
#20
1!
1.
1-
1*
#40
0!
0.
0-
1+
0*
#60
1!
1.
1-
1*
#80
0!
0.
0-
1,
0+
0*
#100
1!
1.
1-
1*
#120
0!
0.
0-
1+
0*
#140
1!
1.
1-
1*
